fewsats/__init__.py
fewsats/_modidx.py
fewsats/core.py
fewsats/l402.py
fewsats-0.0.22.dist-info/LICENSE
fewsats-0.0.22.dist-info/METADATA
fewsats-0.0.22.dist-info/WHEEL
fewsats-0.0.22.dist-info/entry_points.txt
fewsats-0.0.22.dist-info/top_level.txt
fewsats-0.0.22.dist-info/RECORD
