Metadata-Version: 2.2
Name: fewsats
Version: 0.0.22
Summary: Python SDK for Fewsats
Home-page: https://github.com/Fewsats/fewsats-python
Author: Jordi Montes, Pol Alvarez, Albert Serven
Author-email: jordi@fewsats.com, pol@fewsats.com, albert@fewsats.com
License: Apache Software License 2.0
Keywords: nbdev jupyter notebook python
Classifier: Development Status :: 4 - Beta
Classifier: Intended Audience :: Developers
Classifier: Natural Language :: English
Classifier: Programming Language :: Python :: 3.7
Classifier: Programming Language :: Python :: 3.8
Classifier: Programming Language :: Python :: 3.9
Classifier: Programming Language :: Python :: 3.10
Classifier: Programming Language :: Python :: 3.11
Classifier: Programming Language :: Python :: 3.12
Classifier: License :: OSI Approved :: Apache Software License
Requires-Python: >=3.7
License-File: LICENSE
Requires-Dist: fastcore
Requires-Dist: httpx
Requires-Dist: python-dotenv
Provides-Extra: dev
Requires-Dist: claudette; extra == "dev"
Requires-Dist: nbdev; extra == "dev"
Dynamic: author
Dynamic: author-email
Dynamic: classifier
Dynamic: description
Dynamic: description-content-type
Dynamic: home-page
Dynamic: keywords
Dynamic: license
Dynamic: provides-extra
Dynamic: requires-dist
Dynamic: requires-python
Dynamic: summary
